threadingpg/__init__.py
threadingpg/condition.py
threadingpg/controllers.py
threadingpg/data.py
threadingpg/query.py
threadingpg/types.py
threadingpg-0.0.6.dist-info/METADATA
threadingpg-0.0.6.dist-info/WHEEL
threadingpg-0.0.6.dist-info/licenses/LICENSE
threadingpg-0.0.6.dist-info/RECORD
