Metadata-Version: 2.1
Name: threadingpg
Version: 0.0.6
Summary: Simple control 'psycopg2'(PostgreSQL).
Project-URL: Homepage, https://github.com/chorong8883/threadingpg
Author-email: Chor <chorong8883@gmail.com>
License-File: LICENSE
Keywords: postgres,postgresql,thread,thread postgresql,threading postgresql
Classifier: License :: OSI Approved :: MIT License
Classifier: Operating System :: MacOS
Classifier: Operating System :: POSIX :: Linux
Classifier: Programming Language :: Python :: 3.10
Requires-Python: >=3.10
Requires-Dist: psycopg2>=2.9.4
